gleitzeit/__init__.py
gleitzeit/client.py
gleitzeit/registry.py
gleitzeit/api/__init__.py
gleitzeit/api/client.py
gleitzeit/api/main.py
gleitzeit/api/requirements.txt
gleitzeit/api/run_server.py
gleitzeit/cli/__init__.py
gleitzeit/cli/config.py
gleitzeit/cli/gleitzeit_cli.py
gleitzeit/cli/main.py
gleitzeit/cli/main_minimal.py
gleitzeit/cli/workflow.py
gleitzeit/cli/commands/__init__.py
gleitzeit/cli/commands/dev.py
gleitzeit/cli/commands/status.py
gleitzeit/cli/commands/submit.py
gleitzeit/common/__init__.py
gleitzeit/common/circuit_breaker.py
gleitzeit/common/health_monitor.py
gleitzeit/common/load_balancer.py
gleitzeit/common/metrics.py
gleitzeit/common/shutdown.py
gleitzeit/core/__init__.py
gleitzeit/core/batch_processor.py
gleitzeit/core/dependency_tracker.py
gleitzeit/core/error_formatter.py
gleitzeit/core/error_handler.py
gleitzeit/core/errors.py
gleitzeit/core/events.py
gleitzeit/core/execution_engine.py
gleitzeit/core/jsonrpc.py
gleitzeit/core/models.py
gleitzeit/core/protocol.py
gleitzeit/core/retry_manager.py
gleitzeit/core/scheduler.py
gleitzeit/core/workflow_loader.py
gleitzeit/core/workflow_manager.py
gleitzeit/execution/__init__.py
gleitzeit/execution/docker_executor.py
gleitzeit/hub/__init__.py
gleitzeit/hub/base.py
gleitzeit/hub/configs.py
gleitzeit/hub/docker_hub.py
gleitzeit/hub/mcp_hub.py
gleitzeit/hub/ollama_hub.py
gleitzeit/hub/resource_manager.py
gleitzeit/integrations/__init__.py
gleitzeit/orchestration/__init__.py
gleitzeit/orchestration/ollama_pool.py
gleitzeit/persistence/__init__.py
gleitzeit/persistence/base.py
gleitzeit/persistence/factory.py
gleitzeit/persistence/redis_backend.py
gleitzeit/persistence/sqlite_backend.py
gleitzeit/persistence/unified_persistence.py
gleitzeit/persistence/unified_redis.py
gleitzeit/persistence/unified_sql_backend.py
gleitzeit/persistence/unified_sqlalchemy.py
gleitzeit/protocols/__init__.py
gleitzeit/protocols/llm_protocol.py
gleitzeit/protocols/mcp_protocol.py
gleitzeit/protocols/python_protocol.py
gleitzeit-0.0.5.dist-info/licenses/LICENSE
gleitzeit-0.0.5.dist-info/METADATA
gleitzeit-0.0.5.dist-info/WHEEL
gleitzeit-0.0.5.dist-info/entry_points.txt
gleitzeit-0.0.5.dist-info/top_level.txt
gleitzeit-0.0.5.dist-info/RECORD
