Metadata-Version: 2.4
Name: gleitzeit
Version: 0.0.5
Summary: Unified workflow orchestration system with LLM, Python, and MCP support
Home-page: https://github.com/leifmarkthaler/gleitzeit
Author: Leif Markthaler
Author-email: Leif Markthaler <leif.markthaler@gmail.com>
Maintainer-email: Leif Markthaler <leif.markthaler@gmail.com>
License-Expression: MIT
Project-URL: Homepage, https://github.com/leifmarkthaler/gleitzeit
Project-URL: Documentation, https://github.com/leifmarkthaler/gleitzeit#readme
Project-URL: Source, https://github.com/leifmarkthaler/gleitzeit
Project-URL: Bug Reports, https://github.com/leifmarkthaler/gleitzeit/issues
Project-URL: Changelog, https://github.com/leifmarkthaler/gleitzeit/blob/main/CHANGELOG.md
Keywords: workflow,orchestration,automation,unified-persistence,hub-provider,async,llm,mcp,model-context-protocol,task-automation,python-execution,docker,redis,sqlite
Classifier: Development Status :: 4 - Beta
Classifier: Intended Audience :: Developers
Classifier: Operating System :: OS Independent
Classifier: Programming Language :: Python :: 3
Classifier: Programming Language :: Python :: 3.8
Classifier: Programming Language :: Python :: 3.9
Classifier: Programming Language :: Python :: 3.10
Classifier: Programming Language :: Python :: 3.11
Classifier: Programming Language :: Python :: 3.12
Classifier: Topic :: Software Development :: Libraries :: Python Modules
Classifier: Topic :: System :: Distributed Computing
Classifier: Topic :: Software Development :: Libraries :: Application Frameworks
Classifier: Typing :: Typed
Requires-Python: >=3.8
License-File: LICENSE
Requires-Dist: click>=8.0.0
Requires-Dist: pydantic>=2.0.0
Requires-Dist: pyyaml>=6.0.0
Requires-Dist: aiohttp>=3.12.0
Requires-Dist: jsonschema>=4.0.0
Requires-Dist: aiosqlite>=0.21.0
Requires-Dist: redis>=4.5.0
Requires-Dist: aiofiles>=24.1.0
Requires-Dist: httpx>=0.24.0
Provides-Extra: dev
Requires-Dist: pytest>=7.0.0; extra == "dev"
Requires-Dist: pytest-asyncio>=0.21.0; extra == "dev"
Requires-Dist: pytest-cov>=4.0.0; extra == "dev"
Requires-Dist: pytest-mock>=3.11.0; extra == "dev"
Requires-Dist: black>=23.0.0; extra == "dev"
Requires-Dist: mypy>=1.0.0; extra == "dev"
Requires-Dist: ruff>=0.1.0; extra == "dev"
Requires-Dist: pre-commit>=3.0.0; extra == "dev"
Requires-Dist: coverage>=7.0.0; extra == "dev"
Provides-Extra: llm
Requires-Dist: ollama>=0.1.0; extra == "llm"
Requires-Dist: openai>=1.0.0; extra == "llm"
Requires-Dist: anthropic>=0.7.0; extra == "llm"
Provides-Extra: docker
Requires-Dist: docker>=6.0.0; extra == "docker"
Provides-Extra: all
Requires-Dist: gleitzeit[dev]; extra == "all"
Requires-Dist: gleitzeit[llm]; extra == "all"
Requires-Dist: gleitzeit[docker]; extra == "all"
Dynamic: author
Dynamic: home-page
Dynamic: license-file
Dynamic: requires-python
